MANIFEST.in
setup.py
django_podcast_client.egg-info/PKG-INFO
django_podcast_client.egg-info/SOURCES.txt
django_podcast_client.egg-info/dependency_links.txt
django_podcast_client.egg-info/requires.txt
django_podcast_client.egg-info/top_level.txt
podcast_client/__init__.py
podcast_client/admin.py
podcast_client/celery.py
podcast_client/models.py
podcast_client/tasks.py
podcast_client/urls.py
podcast_client/views.py
podcast_client/api/__init__.py
podcast_client/api/serializers.py
podcast_client/management/__init__.py
podcast_client/management/commands/__init__.py
podcast_client/management/commands/podcast.py
podcast_client/migrations/0001_initial.py
podcast_client/migrations/0002_auto__chg_field_podcastchannel_slug__add_field_podcastitem_slug__add_f.py
podcast_client/migrations/__init__.py
podcast_client/static/css/podcast_client.css
podcast_client/static/fonts/glyphicons-halflings-regular.eot
podcast_client/static/fonts/glyphicons-halflings-regular.svg
podcast_client/static/fonts/glyphicons-halflings-regular.ttf
podcast_client/static/fonts/glyphicons-halflings-regular.woff
podcast_client/static/img/glyphicons-halflings-white.png
podcast_client/static/img/glyphicons-halflings.png
podcast_client/static/js/podcast_client.js
podcast_client/templates/podcast_client/.home.html.swp
podcast_client/templates/podcast_client/home.html