Metadata-Version: 1.1
Name: django-podcast-client
Version: 0.2.1
Summary: A client for downloading and organzing podcasts.
Home-page: http://github.com/jsatt/django-podcast-client
Author: Jeremy Satterfield
Author-email: jsatt22@gmail.com
License: GNU General Public License v3 (GPLv3)
Platform: UNKNOWN
Classifier: Development Status :: 4 - Beta
Classifier: Environment :: Web Environment
Classifier: Framework :: Django
Classifier: Intended Audience :: End Users/Desktop
Classifier: License :: OSI Approved :: GNU General Public License v3 (GPLv3)
Classifier: Natural Language :: English
Classifier: Operating System :: OS Independent
Classifier: Programming Language :: Python
Classifier: Topic :: Utilities
